{
  "oc_ace_connection_type_t": {
    "OC_CONN_AUTH_CRYPT": "",
    "OC_CONN_ANON_CLEAR": ""
  },
  "oc_ace_permissions_t": {
    "OC_PERM_NONE": "",
    "OC_PERM_CREATE": "",
    "OC_PERM_RETRIEVE": "",
    "OC_PERM_UPDATE": "",
    "OC_PERM_DELETE": "",
    "OC_PERM_NOTIFY": ""
  },
  "oc_ace_subject_type_t": {
    "OC_SUBJECT_UUID": "",
    "OC_SUBJECT_ROLE": "",
    "OC_SUBJECT_CONN": ""
  },
  "oc_ace_wildcard_t": {
    "OC_ACE_NO_WC": "",
    "OC_ACE_WC_ALL": "",
    "OC_ACE_WC_ALL_SECURED": "",
    "OC_ACE_WC_ALL_PUBLIC": ""
  },
  "oc_blockwise_role_t": {
    "OC_BLOCKWISE_CLIENT": "",
    "OC_BLOCKWISE_SERVER": ""
  },
  "oc_discovery_flags_t": {
    "OC_STOP_DISCOVERY": "",
    "OC_CONTINUE_DISCOVERY": ""
  },
  "oc_qos_t": {
    "HIGH_QOS": "",
    "LOW_QOS": ""
  },
  "oc_cloud_error_t": {
    "CLOUD_OK": "",
    "CLOUD_ERROR_RESPONSE": "",
    "CLOUD_ERROR_CONNECT": "",
    "CLOUD_ERROR_REFRESH_ACCESS_TOKEN": ""
  },
  "oc_cloud_status_t": {
    "OC_CLOUD_INITIALIZED": "",
    "OC_CLOUD_REGISTERED": "",
    "OC_CLOUD_LOGGED_IN": "",
    "OC_CLOUD_TOKEN_EXPIRY": "",
    "OC_CLOUD_REFRESHED_TOKEN": "",
    "OC_CLOUD_LOGGED_OUT": "",
    "OC_CLOUD_FAILURE": "",
    "OC_CLOUD_DEREGISTERED": ""
  },
  "oc_cps_t": {
    "OC_CPS_UNINITIALIZED": "",
    "OC_CPS_READYTOREGISTER": "",
    "OC_CPS_REGISTERING": "",
    "OC_CPS_REGISTERED": "",
    "OC_CPS_FAILED": ""
  },
  "tcp_csm_state_t": {
    "CSM_NONE": "",
    "CSM_SENT": "",
    "CSM_DONE": "",
    "CSM_ERROR": ""
  },
  "oc_sec_credtype_t": {
    "OC_CREDTYPE_NULL": "",
    "OC_CREDTYPE_PSK": "",
    "OC_CREDTYPE_CERT": ""
  },
  "oc_sec_credusage_t": {
    "OC_CREDUSAGE_NULL": "",
    "OC_CREDUSAGE_TRUSTCA": "",
    "OC_CREDUSAGE_IDENTITY_CERT": "",
    "OC_CREDUSAGE_ROLE_CERT": "",
    "OC_CREDUSAGE_MFG_TRUSTCA": "",
    "OC_CREDUSAGE_MFG_CERT": ""
  },
  "oc_sec_encoding_t": {
    "OC_ENCODING_UNSUPPORTED": "",
    "OC_ENCODING_BASE64": "",
    "OC_ENCODING_RAW": "",
    "OC_ENCODING_PEM": "",
    "OC_ENCODING_HANDLE": ""
  },
  "ocf_version_t": {
    "OCF_VER_1_0_0": "",
    "OIC_VER_1_1_0": ""
  },
  "transport_flags": {
    "DISCOVERY": "",
    "SECURED": "",
    "IPV4": "",
    "IPV6": "",
    "TCP": "",
    "GATT": "",
    "MULTICAST": ""
  },
  "oc_enum_t": {
    "OC_ENUM_ABORTED": "",
    "OC_ENUM_ACTIVE": "",
    "OC_ENUM_AIRDRY": "",
    "OC_ENUM_ARMEDAWAY": "",
    "OC_ENUM_ARMEDINSTANT": "",
    "OC_ENUM_ARMEDMAXIMUM": "",
    "OC_ENUM_ARMEDNIGHTSTAY": "",
    "OC_ENUM_ARMEDSTAY": "",
    "OC_ENUM_AROMA": "",
    "OC_ENUM_AI": "",
    "OC_ENUM_AUTO": "",
    "OC_ENUM_BOILING": "",
    "OC_ENUM_BREWING": "",
    "OC_ENUM_CANCELLED": "",
    "OC_ENUM_CIRCULATING": "",
    "OC_ENUM_CLEANING": "",
    "OC_ENUM_CLOTHES": "",
    "OC_ENUM_COMPLETED": "",
    "OC_ENUM_COOL": "",
    "OC_ENUM_DELICATE": "",
    "OC_ENUM_DISABLED": "",
    "OC_ENUM_DOWN": "",
    "OC_ENUM_DUAL": "",
    "OC_ENUM_DRY": "",
    "OC_ENUM_ENABLED": "",
    "OC_ENUM_EXTENDED": "",
    "OC_ENUM_FAN": "",
    "OC_ENUM_FAST": "",
    "OC_ENUM_FILTERMATERIAL": "",
    "OC_ENUM_FOCUSED": "",
    "OC_ENUM_GRINDING": "",
    "OC_ENUM_HEATING": "",
    "OC_ENUM_HEAVY": "",
    "OC_ENUM_IDLE": "",
    "OC_ENUM_INK": "",
    "OC_ENUM_INKBLACK": "",
    "OC_ENUM_INKCYAN": "",
    "OC_ENUM_INKMAGENTA": "",
    "OC_ENUM_INKTRICOLOUR": "",
    "OC_ENUM_INKYELLOW": "",
    "OC_ENUM_KEEPWARM": "",
    "OC_ENUM_NORMAL": "",
    "OC_ENUM_NOTSUPPORTED": "",
    "OC_ENUM_PAUSE": "",
    "OC_ENUM_PENDING": "",
    "OC_ENUM_PENDINGHELD": "",
    "OC_ENUM_PERMAPRESS": "",
    "OC_ENUM_PREWASH": "",
    "OC_ENUM_PROCESSING": "",
    "OC_ENUM_PURE": "",
    "OC_ENUM_QUICK": "",
    "OC_ENUM_QUIET": "",
    "OC_ENUM_RINSE": "",
    "OC_ENUM_SECTORED": "",
    "OC_ENUM_SILENT": "",
    "OC_ENUM_SLEEP": "",
    "OC_ENUM_SMART": "",
    "OC_ENUM_SPOT": "",
    "OC_ENUM_STEAM": "",
    "OC_ENUM_STOPPED": "",
    "OC_ENUM_SPIN": "",
    "OC_ENUM_TESTING": "",
    "OC_ENUM_TONER": "",
    "OC_ENUM_TONERBLACK": "",
    "OC_ENUM_TONERCYAN": "",
    "OC_ENUM_TONERMAGENTA": "",
    "OC_ENUM_TONERYELLOW": "",
    "OC_ENUM_WARM": "",
    "OC_ENUM_WASH": "",
    "OC_ENUM_WET": "",
    "OC_ENUM_WIND": "",
    "OC_ENUM_WRINKLEPREVENT": "",
    "OC_ENUM_ZIGZAG": ""
  },
  "oc_pos_description_t": {
    "OC_POS_UNKNOWN": "",
    "OC_POS_TOP": "",
    "OC_POS_BOTTOM": "",
    "OC_POS_LEFT": "",
    "OC_POS_RIGHT": "",
    "OC_POS_CENTRE": "",
    "OC_POS_TOPLEFT": "",
    "OC_POS_BOTTOMLEFT": "",
    "OC_POS_CENTRELEFT": "",
    "OC_POS_CENTRERIGHT": "",
    "OC_POS_BOTTOMRIGHT": "",
    "OC_POS_TOPRIGHT": "",
    "OC_POS_TOPCENTRE": "",
    "OC_POS_BOTTOMCENTRE": ""
  },
  "pool": {
    "BYTE_POOL": "",
    "INT_POOL": "",
    "DOUBLE_POOL": ""
  },
  "oc_interface_event_t": {
    "NETWORK_INTERFACE_DOWN": "",
    "NETWORK_INTERFACE_UP": ""
  },
  "oc_sp_types_t": {
    "OC_SP_BASELINE": "",
    "OC_SP_BLACK": "",
    "OC_SP_BLUE": "",
    "OC_SP_PURPLE": ""
  },
  "oc_rep_value_type_t": {
    "OC_REP_NIL": "",
    "OC_REP_INT": "",
    "OC_REP_DOUBLE": "",
    "OC_REP_BOOL": "",
    "OC_REP_BYTE_STRING": "",
    "OC_REP_STRING": "",
    "OC_REP_OBJECT": "",
    "OC_REP_ARRAY": "",
    "OC_REP_INT_ARRAY": "",
    "OC_REP_DOUBLE_ARRAY": "",
    "OC_REP_BOOL_ARRAY": "",
    "OC_REP_BYTE_STRING_ARRAY": "",
    "OC_REP_STRING_ARRAY": "",
    "OC_REP_OBJECT_ARRAY": ""
  },
  "oc_content_format_t": {
    "TEXT_PLAIN": "",
    "TEXT_XML": "",
    "TEXT_CSV": "",
    "TEXT_HTML": "",
    "IMAGE_GIF": "",
    "IMAGE_JPEG": "",
    "IMAGE_PNG": "",
    "IMAGE_TIFF": "",
    "AUDIO_RAW": "",
    "VIDEO_RAW": "",
    "APPLICATION_LINK_FORMAT": "",
    "APPLICATION_XML": "",
    "APPLICATION_OCTET_STREAM": "",
    "APPLICATION_RDF_XML": "",
    "APPLICATION_SOAP_XML": "",
    "APPLICATION_ATOM_XML": "",
    "APPLICATION_XMPP_XML": "",
    "APPLICATION_EXI": "",
    "APPLICATION_FASTINFOSET": "",
    "APPLICATION_SOAP_FASTINFOSET": "",
    "APPLICATION_JSON": "",
    "APPLICATION_X_OBIX_BINARY": "",
    "APPLICATION_CBOR": "",
    "APPLICATION_VND_OCF_CBOR": ""
  },
  "oc_core_resource_t": {
    "OCF_P": "",
    "OCF_CON": "",
    "OCF_INTROSPECTION_WK": "",
    "OCF_INTROSPECTION_DATA": "",
    "OCF_RES": "",
    "OCF_MNT": "",
    "OCF_COAPCLOUDCONF": "",
    "OCF_SW_UPDATE": "",
    "OCF_SEC_DOXM": "",
    "OCF_SEC_PSTAT": "",
    "OCF_SEC_ACL": "",
    "OCF_SEC_AEL": "",
    "OCF_SEC_CRED": "",
    "OCF_SEC_SDI": "",
    "OCF_SEC_SP": "",
    "OCF_SEC_CSR": "",
    "OCF_SEC_ROLES": "",
    "OCF_D": ""
  },
  "oc_event_callback_retval_t": {
    "OC_EVENT_DONE": "",
    "OC_EVENT_CONTINUE": ""
  },
  "oc_interface_mask_t": {
    "OC_IF_BASELINE": "",
    "OC_IF_LL": "",
    "OC_IF_B": "",
    "OC_IF_R": "",
    "OC_IF_RW": "",
    "OC_IF_A": "",
    "OC_IF_S": "",
    "OC_IF_CREATE": ""
  },
  "oc_method_t": {
    "OC_GET": "",
    "OC_POST": "",
    "OC_PUT": "",
    "OC_DELETE": ""
  },
  "oc_resource_properties_t": {
    "OC_DISCOVERABLE": "",
    "OC_OBSERVABLE": "",
    "OC_SECURE": "",
    "OC_PERIODIC": ""
  },
  "oc_status_t": {
    "OC_STATUS_OK": "",
    "OC_STATUS_CREATED": "",
    "OC_STATUS_CHANGED": "",
    "OC_STATUS_DELETED": "",
    "OC_STATUS_NOT_MODIFIED": "",
    "OC_STATUS_BAD_REQUEST": "",
    "OC_STATUS_UNAUTHORIZED": "",
    "OC_STATUS_BAD_OPTION": "",
    "OC_STATUS_FORBIDDEN": "",
    "OC_STATUS_NOT_FOUND": "",
    "OC_STATUS_METHOD_NOT_ALLOWED": "",
    "OC_STATUS_NOT_ACCEPTABLE": "",
    "OC_STATUS_REQUEST_ENTITY_TOO_LARGE": "",
    "OC_STATUS_UNSUPPORTED_MEDIA_TYPE": "",
    "OC_STATUS_INTERNAL_SERVER_ERROR": "",
    "OC_STATUS_NOT_IMPLEMENTED": "",
    "OC_STATUS_BAD_GATEWAY": "",
    "OC_STATUS_SERVICE_UNAVAILABLE": "",
    "OC_STATUS_GATEWAY_TIMEOUT": "",
    "OC_STATUS_PROXYING_NOT_SUPPORTED": "",
    "__NUM_OC_STATUS_CODES__": "",
    "OC_IGNORE": "",
    "OC_PING_TIMEOUT": ""
  },
  "oc_session_state_t": {
    "OC_SESSION_CONNECTED": "",
    "OC_SESSION_DISCONNECTED": ""
  },
  "oc_swupdate_result_t": {
    "OC_SWUPDATE_RESULT_IDLE": "",
    "OC_SWUPDATE_RESULT_SUCCESS": "",
    "OC_SWUPDATE_RESULT_LESS_RAM": "",
    "OC_SWUPDATE_RESULT_LESS_FLASH": "",
    "OC_SWUPDATE_RESULT_CONN_FAIL": "",
    "OC_SWUPDATE_RESULT_SVV_FAIL": "",
    "OC_SWUPDATE_RESULT_INVALID_URL": "",
    "OC_SWUPDATE_RESULT_UPGRADE_FAIL": ""
  }
}
